MANIFEST.in
README.md
setup.cfg
setup.py
django_minio/__init__.py
django_minio/storage.py
django_minio.egg-info/PKG-INFO
django_minio.egg-info/SOURCES.txt
django_minio.egg-info/dependency_links.txt
django_minio.egg-info/requires.txt
django_minio.egg-info/top_level.txt