Metadata-Version: 2.1
Name: django-minio
Version: 2.0
Summary: Django app to use Minio Server as file storage.
Home-page: https://github.com/maddevsio/django_minio
Author: Belek Abylov
Author-email: abylov.belek@gmail.com
License: MIT
Keywords: minio storage files
Platform: UNKNOWN
Classifier: Environment :: Web Environment
Classifier: Framework :: Django :: 2.0
Classifier: Intended Audience :: Developers
Classifier: License :: OSI Approved :: BSD License
Classifier: Operating System :: OS Independent
Classifier: Programming Language :: Python :: 3.6
Classifier: Topic :: Software Development :: Libraries :: Python Modules
Provides-Extra: dev
